Lava/Input.py
Lava/__init__.py
lava_engine-0.1.0.dist-info/LICENSE
lava_engine-0.1.0.dist-info/METADATA
lava_engine-0.1.0.dist-info/WHEEL
lava_engine-0.1.0.dist-info/top_level.txt
lava_engine-0.1.0.dist-info/RECORD
