Metadata-Version: 2.1
Name: lava-engine
Version: 0.1.0
Summary: A powerful 🚀and simple 🧔🏻‍♂️ terminal 💻 game engine
Author-email: Revitalize <boxeigit@gmail.com>
Project-URL: Homepage, https://github.com/RevitalizeStudio/Lava
Project-URL: Bug Tracker, https://github.com/RevitalizeStudio/Lava/issues
Classifier: Programming Language :: Python :: 3
Classifier: License :: OSI Approved :: MIT License
Classifier: Operating System :: OS Independent
Requires-Python: >=3.7
License-File: LICENSE
